Paginator.py
discord.py_pagination-0.0.5.dist-info/LICENSE
discord.py_pagination-0.0.5.dist-info/METADATA
discord.py_pagination-0.0.5.dist-info/WHEEL
discord.py_pagination-0.0.5.dist-info/top_level.txt
discord.py_pagination-0.0.5.dist-info/RECORD
